[
  {
    "name": "rur",
    "value": "\"RVA\\05443521916834\\0541672357031:01f79699bc7f2f11ecbb528c951b70176a4d1d421c839374ff0c951e11baffa5f18745d4\"",
    "domain": ".instagram.com",
    "path": "/",
    "expires": -1,
    "size": 110,
    "httpOnly": true,
    "secure": true,
    "session": true,
    "sameParty": false,
    "sourceScheme": "Secure",
    "sourcePort": 443
  },
  {
    "name": "shbid",
    "value": "\"14488\\05443521916834\\0541672357023:01f7dcaf4820db6addb01e9df28b93f0857181c5f3a45c3f2878381d09afc10c7dcc878d\"",
    "domain": ".instagram.com",
    "path": "/",
    "expires": 1641425823.771748,
    "size": 114,
    "httpOnly": true,
    "secure": true,
    "session": false,
    "sameParty": false,
    "sourceScheme": "Secure",
    "sourcePort": 443
  },
  {
    "name": "shbts",
    "value": "\"1640821023\\05443521916834\\0541672357023:01f7466bdc8dcfe84fb06c7606cdc5012ea43d0700d4cc8e7aaf70bfe41e41385aad6a87\"",
    "domain": ".instagram.com",
    "path": "/",
    "expires": 1641425823.771815,
    "size": 119,
    "httpOnly": true,
    "secure": true,
    "session": false,
    "sameParty": false,
    "sourceScheme": "Secure",
    "sourcePort": 443
  },
  {
    "name": "sessionid",
    "value": "43521916834%3ArjsgJVjKFdv5s3%3A12",
    "domain": ".instagram.com",
    "path": "/",
    "expires": 1672357023.31009,
    "size": 42,
    "httpOnly": true,
    "secure": true,
    "session": false,
    "sameParty": false,
    "sourceScheme": "Secure",
    "sourcePort": 443
  },
  {
    "name": "csrftoken",
    "value": "rZdEfm76kvTEtt5TlTBeFKuNKxsYp2Z1",
    "domain": ".instagram.com",
    "path": "/",
    "expires": 1672270631.162006,
    "size": 41,
    "httpOnly": false,
    "secure": true,
    "session": false,
    "sameParty": false,
    "sourceScheme": "Secure",
    "sourcePort": 443
  },
  {
    "name": "ig_nrcb",
    "value": "1",
    "domain": ".instagram.com",
    "path": "/",
    "expires": 1672357017.187734,
    "size": 8,
    "httpOnly": false,
    "secure": true,
    "session": false,
    "sameParty": false,
    "sourceScheme": "Secure",
    "sourcePort": 443
  },
  {
    "name": "ds_user_id",
    "value": "43521916834",
    "domain": ".instagram.com",
    "path": "/",
    "expires": 1648597031.162221,
    "size": 21,
    "httpOnly": false,
    "secure": true,
    "session": false,
    "sameParty": false,
    "sourceScheme": "Secure",
    "sourcePort": 443
  },
  {
    "name": "ig_did",
    "value": "E764A7A1-38CD-4002-BAEA-10486C8F124F",
    "domain": ".instagram.com",
    "path": "/",
    "expires": 1703893017.187543,
    "size": 42,
    "httpOnly": true,
    "secure": true,
    "session": false,
    "sameParty": false,
    "sourceScheme": "Secure",
    "sourcePort": 443
  },
  {
    "name": "mid",
    "value": "YczxGAALAAHam1R7VGEamyq9RsIv",
    "domain": ".instagram.com",
    "path": "/",
    "expires": 1703893017.187264,
    "size": 31,
    "httpOnly": false,
    "secure": true,
    "session": false,
    "sameParty": false,
    "sourceScheme": "Secure",
    "sourcePort": 443
  }
]